{"FS1_FSA": {"venting": {"mech_extract": {"number": 1, "flow": 6.0}, "mech_supply": {"number": 0, "flow": 0}, "stair_aov": {"area": 1.0}, "natural_openings": []}, "is_sprinklered": true, "door_opening_times": {"opening_apartment": 60.0, "closing_apartment": null, "opening_stair": 0.0, "closing_stair": null}, "end_time": 300.0, "tenability": {"2m": 87.593452, "4m": 127.35462, "15m": []}, "min_pressure": NaN, "worst_condition": {"stair_temp": 20.913436, "stair_vis": 24.24178}}, "FS2_ FSA": {"venting": {"mech_extract": {"number": 1, "flow": 6.0}, "mech_supply": {"number": 0, "flow": 0}, "stair_aov": {"area": 1.0}, "natural_openings": []}, "is_sprinklered": true, "door_opening_times": {"opening_apartment": 60.0, "closing_apartment": null, "opening_stair": 0.0, "closing_stair": null}, "end_time": 300.0, "tenability": {"2m": 136.09408, "4m": 155.74951, "15m": []}, "min_pressure": NaN, "worst_condition": {"stair_temp": 20.549288, "stair_vis": 30.0}}, "FS2_FSA_2": {"venting": {"mech_extract": {"number": 1, "flow": 6.0}, "mech_supply": {"number": 0, "flow": 0}, "stair_aov": {"area": 1.0}, "natural_openings": []}, "is_sprinklered": true, "door_opening_times": {"opening_apartment": 60.0, "closing_apartment": null, "opening_stair": 0.0, "closing_stair": null}, "end_time": 300.0, "tenability": {"2m": 178.12688, "4m": 191.52619, "15m": []}, "min_pressure": NaN, "worst_condition": {"stair_temp": 20.553801, "stair_vis": 30.0}}, "FS3_FSA": {"venting": {"mech_extract": {"number": 1, "flow": 4.0}, "mech_supply": {"number": 0, "flow": 0}, "stair_aov": {"area": 1.0}, "natural_openings": []}, "is_sprinklered": true, "door_opening_times": {"opening_apartment": 60.0, "closing_apartment": null, "opening_stair": 0.0, "closing_stair": null}, "end_time": 300.0, "tenability": {"2m": 198.99046, "4m": 159.94851, "15m": []}, "min_pressure": NaN, "worst_condition": {"stair_temp": 21.823981, "stair_vis": 10.406929}}, "FS4_FSA": {"venting": {"mech_extract": {"number": 1, "flow": 4.0}, "mech_supply": {"number": 0, "flow": 0}, "stair_aov": {"area": 1.0}, "natural_openings": []}, "is_sprinklered": true, "door_opening_times": {"opening_apartment": 60.0, "closing_apartment": null, "opening_stair": 0.0, "closing_stair": null}, "end_time": 300.0, "tenability": {"2m": 31.490164, "4m": 31.586325, "15m": []}, "min_pressure": NaN, "worst_condition": {"stair_temp": 20.242405, "stair_vis": 30.0}}, "FS5_MOE": {"venting": {"mech_extract": {"number": 1, "flow": 4.0}, "mech_supply": {"number": 0, "flow": 0}, "stair_aov": {"area": 1.0}, "natural_openings": []}, "is_sprinklered": true, "door_opening_times": {"opening_apartment": 59.0, "closing_apartment": 79.0, "opening_stair": 74.0, "closing_stair": 94.0}, "end_time": 300.0, "tenability": {"time": 88.40226999999999}, "min_pressure": -59.091895, "worst_condition": {"stair_temp": 20.04136, "stair_vis": 30.0, "cc_vis": 0.086795523, "cc_temp": 245.59178}}, "FS6_FSA": {"venting": {"mech_extract": {"number": 1, "flow": 5.0}, "mech_supply": {"number": 0, "flow": 0}, "stair_aov": {"area": 1.0}, "natural_openings": [2.1, 0.2, 0.2]}, "is_sprinklered": true, "door_opening_times": {"opening_apartment": 59.0, "closing_apartment": 60.0, "opening_stair": 0, "closing_stair": null}, "end_time": 300.0, "tenability": {"2m": 109.04944, "4m": 98.667679, "15m": 35.739532, "6m": 79.973466, "8m": 91.389351, "10m": 59.673382, "11m": 58.880207, "13m": 60.748362}, "min_pressure": -29.206429, "worst_condition": {"stair_temp": 20.128128, "stair_vis": 30.0}}, "FS7_FSA": {"venting": {"mech_extract": {"number": 1, "flow": 5.0}, "mech_supply": {"number": 0, "flow": 0}, "stair_aov": {"area": 1.0}, "natural_openings": [2.1, 0.2, 0.2]}, "is_sprinklered": true, "door_opening_times": {"opening_apartment": 59.0, "closing_apartment": 60.0, "opening_stair": 0, "closing_stair": null}, "end_time": 300.0, "tenability": {"2m": 73.384422, "4m": 79.859028, "15m": 110.93777, "1m": 96.913651, "6m": 99.332772}, "min_pressure": -22.586305, "worst_condition": {"stair_temp": 47.308718, "stair_vis": 0.47683644}}}